go_cli.py
go_questionary/__init__.py
go_questionary/constants.py
go_questionary/form.py
go_questionary/prompt.py
go_questionary/question.py
go_questionary/utils.py
go_questionary/version.py
go_questionary/prompts/__init__.py
go_questionary/prompts/autocomplete.py
go_questionary/prompts/checkbox.py
go_questionary/prompts/common.py
go_questionary/prompts/confirm.py
go_questionary/prompts/password.py
go_questionary/prompts/path.py
go_questionary/prompts/rawselect.py
go_questionary/prompts/select.py
go_questionary/prompts/text.py
gorilla_cli-0.0.10.dist-info/LICENSE
gorilla_cli-0.0.10.dist-info/METADATA
gorilla_cli-0.0.10.dist-info/WHEEL
gorilla_cli-0.0.10.dist-info/entry_points.txt
gorilla_cli-0.0.10.dist-info/top_level.txt
gorilla_cli-0.0.10.dist-info/RECORD
