Metadata-Version: 2.1
Name: gorilla-cli
Version: 0.0.10
Summary: LLMs for CLI
Home-page: https://github.com/gorilla-llm/gorilla-cli
Author: Shishir Patil, Tianjun Zhang
Author-email: sgp@berkeley.edu, tianjunz@berkeley.edu
License: Apache 2.0
Platform: UNKNOWN
Classifier: Programming Language :: Python :: 3
Classifier: License :: OSI Approved :: Apache Software License
Classifier: Operating System :: OS Independent
Requires-Python: >=3.6
License-File: LICENSE
